sam2util/__init__.py
sam2util/common.py
sam2util-1.1.3.dist-info/METADATA
sam2util-1.1.3.dist-info/WHEEL
sam2util-1.1.3.dist-info/RECORD
